spm2olca/__init__.py
spm2olca/mappings.py
spm2olca/model.py
spm2olca/pack.py
spm2olca/parser.py
spm2olca/util.py
spm2olca/data/__init__.py
spm2olca/data/units.csv
spm2olca-1.1.0.dist-info/DESCRIPTION.rst
spm2olca-1.1.0.dist-info/METADATA
spm2olca-1.1.0.dist-info/RECORD
spm2olca-1.1.0.dist-info/WHEEL
spm2olca-1.1.0.dist-info/entry_points.txt
spm2olca-1.1.0.dist-info/metadata.json
spm2olca-1.1.0.dist-info/top_level.txt
