Metadata-Version: 2.0
Name: spm2olca
Version: 1.1.0
Summary: SimaPro Method File to olca-schema converter
Home-page: https://github.com/GreenDelta/spm2olca
Author: Michael Srocka
Author-email: michael.srocka@gmail.com
License: MIT
Download-URL: https://github.com/GreenDelta/spm2olca/tarball/v1.0.0
Keywords: converter lca
Platform: UNKNOWN
Classifier: Development Status :: 3 - Alpha
Classifier: Environment :: Console
Classifier: Intended Audience :: Science/Research
Classifier: License :: OSI Approved :: MIT License
Classifier: Programming Language :: Python :: 3.5
Classifier: Topic :: Utilities
